huffman/descendSort.v

module descendSort #
(
parameter DEPTH = 8,
parameter WIDTH = 8

)(
input clock,
input rstn,
input valid,
input [WIDTH -1 :0] [DEPTH - 1:0] in_data,
input [WIDTH -1 :0] [DEPTH - 1:0] in_probab,
output  wire [WIDTH -1 :0] [DEPTH - 1:0] out_data,
output reg ready

);

localparam DEPTH_1 = DEPTH;

  parameter IDLE         = 3'b000;
  parameter START    = 3'b001;
  parameter SORT = 3'b010;
  parameter DONE  = 3'b011;
  parameter INCR_PTR      = 3'b100;
  
  reg [WIDTH -1 :0] [DEPTH - 1:0] in_data_1;
  
  reg [2:0]     sortState;
  reg [2:0]     inputPointer; //TODO
  reg [2:0]     checkPointer; //TODO
  reg [2:0]     counter_1; //TODO
  reg [2:0]     counter_2; //TODO
  reg [WIDTH -1 :0] in_data_2;
  assign out_data = in_data_1;
  
always @ (posedge clock or negedge rstn) begin

	if (~rstn) begin
		//out_data     <= 0;
		ready        <= 1'b0;
		sortState    <= IDLE;
		in_data_1    <= 0;
		inputPointer <= 0;
		checkPointer <= 1;
		counter_1    <= 3'b000;
		counter_2    <= 3'b000;
	end else begin
	
	case (sortState)
	IDLE : begin
		in_data_1 <= valid ? in_data : in_data_1;
		ready     <= valid ? 1'b0 : ready;
		sortState <= valid ? START : IDLE;
		inputPointer <= 0;
		checkPointer <= 0;
		counter_1    <= 3'b000;
		counter_2    <= 3'b000;
	end
	START : begin
		in_data_2 <= in_data_1[inputPointer];
		sortState <= (inputPointer == 3'b111 ) ? DONE : SORT;
		checkPointer <= (inputPointer == 3'b111 ) ? 3'b000 : inputPointer + 3'b001;
	end
	SORT : begin
		in_data_1[inputPointer] <= (in_data_1[inputPointer] < in_data_1[checkPointer]) ? in_data_1[checkPointer] : in_data_1[inputPointer];
		in_data_1[checkPointer] <= (in_data_1[inputPointer] < in_data_1[checkPointer]) ? in_data_1[inputPointer] : in_data_1[checkPointer];
		checkPointer            <= (checkPointer == 3'b111) ? 3'b000 : (checkPointer + 3'b001);
		sortState <= (checkPointer == 3'b111) ? INCR_PTR : SORT;
	end
	INCR_PTR : begin 
		inputPointer <= (inputPointer == 3'b111) ? 3'b000 : (inputPointer + 3'b001);
		sortState 	 <= (inputPointer == 3'b111) ? DONE : START;
	end
	DONE : begin
		//out_data <= in_data_1;
		ready <= 1'b1;
		sortState 	 <= IDLE;
	end
	endcase
	
	
	end



end









endmodule

huffman/descendSort_tb.v
// Verilog testbench created by SSP
// 2022-10-17 22:45:46

`timescale 1ns / 1ps

module descendSort_tb();

reg clk;
reg rstb;

localparam DEPTH = 8;
localparam WIDTH = 8;


reg [WIDTH -1 :0] [DEPTH - 1:0] in_data;
reg [WIDTH -1 :0] [DEPTH - 1:0] in_probab;
wire [WIDTH -1 :0] [DEPTH - 1:0] out_data;


wire [WIDTH -1 :0] out_data0;
wire [WIDTH -1 :0] out_data1;
wire [WIDTH -1 :0] out_data2;
wire [WIDTH -1 :0] out_data3;
wire [WIDTH -1 :0] out_data4;
wire [WIDTH -1 :0] out_data5;
wire [WIDTH -1 :0] out_data6;
wire [WIDTH -1 :0] out_data7;

wire [WIDTH -1 :0] in_data0;
wire [WIDTH -1 :0] in_data1;
wire [WIDTH -1 :0] in_data2;
wire [WIDTH -1 :0] in_data3;
wire [WIDTH -1 :0] in_data4;
wire [WIDTH -1 :0] in_data5;
wire [WIDTH -1 :0] in_data6;
wire [WIDTH -1 :0] in_data7;



assign in_data0 = in_data[0];
assign in_data1 = in_data[1];
assign in_data2 = in_data[2];
assign in_data3 = in_data[3];
assign in_data4 = in_data[4];
assign in_data5 = in_data[5];
assign in_data6 = in_data[6];
assign in_data7 = in_data[7];

 assign out_data0  =  out_data[0];
 assign out_data1  =  out_data[1];
 assign out_data2  =  out_data[2];
 assign out_data3  =  out_data[3];
 assign out_data4  =  out_data[4];
 assign out_data5  =  out_data[5];
 assign out_data6  =  out_data[6];
 assign out_data7  =  out_data[7];








reg valid;
always #1 clk = ~clk;  

initial begin
		$dumpfile("descendSort.vcd");
		$dumpvars(0, descendSort_tb);
		
        end
//Stimulus process
initial begin
//To be inserted
    clk 	<= 0;  
    valid 	<= 1'b0;
    rstb 	<= 0;  
    in_data <= 0;
    #100 rstb <= 1;
    #10
    in_data[0] <= 10;
    in_data[1] <= 5;
    in_data[2] <= 2;
    in_data[3] <= 25;
    in_data[4] <= 6;
    in_data[5] <= 4;
    in_data[6] <= 3;
    in_data[7] <= 44;
    valid 	<= 1;
    #10
    valid 	<= 0;
    #200
    
    $finish;
end











descendSort u_descendSort (


.clock(clk),
.rstn(rstb),
.valid(valid),
.ready(ready),

.in_data(in_data),
.in_probab(in_probab),
.out_data(out_data)




);







endmodule

huffman/descendSort.vcd
$date
	Mon Oct 17 23:40:46 2022
$end
$version
	Icarus Verilog
$end
$timescale
	1ps
$end
$scope module descendSort_tb $end
$var wire 1 ! ready $end
$var wire 8 " out_data7 [7:0] $end
$var wire 8 # out_data6 [7:0] $end
$var wire 8 $ out_data5 [7:0] $end
$var wire 8 % out_data4 [7:0] $end
$var wire 8 & out_data3 [7:0] $end
$var wire 8 ' out_data2 [7:0] $end
$var wire 8 ( out_data1 [7:0] $end
$var wire 8 ) out_data0 [7:0] $end
$var wire 64 * out_data [63:0] $end
$var wire 8 + in_data7 [7:0] $end
$var wire 8 , in_data6 [7:0] $end
$var wire 8 - in_data5 [7:0] $end
$var wire 8 . in_data4 [7:0] $end
$var wire 8 / in_data3 [7:0] $end
$var wire 8 0 in_data2 [7:0] $end
$var wire 8 1 in_data1 [7:0] $end
$var wire 8 2 in_data0 [7:0] $end
$var reg 1 3 clk $end
$var reg 64 4 in_data [63:0] $end
$var reg 64 5 in_probab [63:0] $end
$var reg 1 6 rstb $end
$var reg 1 7 valid $end
$scope module u_descendSort $end
$var wire 1 3 clock $end
$var wire 64 8 in_data [63:0] $end
$var wire 64 9 in_probab [63:0] $end
$var wire 64 : out_data [63:0] $end
$var wire 1 6 rstn $end
$var wire 1 7 valid $end
$var reg 3 ; checkPointer [2:0] $end
$var reg 3 < counter_1 [2:0] $end
$var reg 3 = counter_2 [2:0] $end
$var reg 64 > in_data_1 [63:0] $end
$var reg 8 ? in_data_2 [7:0] $end
$var reg 3 @ inputPointer [2:0] $end
$var reg 1 ! ready $end
$var reg 3 A sortState [2:0] $end
$upscope $end
$upscope $end
$enddefinitions $end
#0
$dumpvars
b0 A
b0 @
bx ?
b0 >
b0 =
b0 <
b1 ;
b0 :
bx 9
b0 8
07
06
bx 5
b0 4
03
b0 2
b0 1
b0 0
b0 /
b0 .
b0 -
b0 ,
b0 +
b0 *
b0 )
b0 (
b0 '
b0 &
b0 %
b0 $
b0 #
b0 "
0!
$end
#1000
13
#2000
03
#3000
13
#4000
03
#5000
13
#6000
03
#7000
13
#8000
03
#9000
13
#10000
03
#11000
13
#12000
03
#13000
13
#14000
03
#15000
13
#16000
03
#17000
13
#18000
03
#19000
13
#20000
03
#21000
13
#22000
03
#23000
13
#24000
03
#25000
13
#26000
03
#27000
13
#28000
03
#29000
13
#30000
03
#31000
13
#32000
03
#33000
13
#34000
03
#35000
13
#36000
03
#37000
13
#38000
03
#39000
13
#40000
03
#41000
13
#42000
03
#43000
13
#44000
03
#45000
13
#46000
03
#47000
13
#48000
03
#49000
13
#50000
03
#51000
13
#52000
03
#53000
13
#54000
03
#55000
13
#56000
03
#57000
13
#58000
03
#59000
13
#60000
03
#61000
13
#62000
03
#63000
13
#64000
03
#65000
13
#66000
03
#67000
13
#68000
03
#69000
13
#70000
03
#71000
13
#72000
03
#73000
13
#74000
03
#75000
13
#76000
03
#77000
13
#78000
03
#79000
13
#80000
03
#81000
13
#82000
03
#83000
13
#84000
03
#85000
13
#86000
03
#87000
13
#88000
03
#89000
13
#90000
03
#91000
13
#92000
03
#93000
13
#94000
03
#95000
13
#96000
03
#97000
13
#98000
03
#99000
13
#100000
16
03
#101000
b0 ;
13
#102000
03
#103000
13
#104000
03
#105000
13
#106000
03
#107000
13
#108000
03
#109000
13
#110000
b101100 +
b11 ,
b100 -
b110 .
b11001 /
b10 0
b101 1
b1010 2
17
b10110000000011000001000000011000011001000000100000010100001010 4
b10110000000011000001000000011000011001000000100000010100001010 8
03
#111000
b101100 "
b11 #
b100 $
b110 %
b11001 &
b10 '
b101 (
b1010 )
b1 A
b10110000000011000001000000011000011001000000100000010100001010 *
b10110000000011000001000000011000011001000000100000010100001010 :
b10110000000011000001000000011000011001000000100000010100001010 >
13
#112000
03
#113000
b1 ;
b10 A
b1010 ?
13
#114000
03
#115000
b10 ;
13
#116000
03
#117000
b11 ;
13
#118000
03
#119000
b1010 &
b11001 )
b100 ;
b10110000000011000001000000011000001010000000100000010100011001 *
b10110000000011000001000000011000001010000000100000010100011001 :
b10110000000011000001000000011000001010000000100000010100011001 >
13
#120000
07
03
#121000
b101 ;
13
#122000
03
#123000
b110 ;
13
#124000
03
#125000
b111 ;
13
#126000
03
#127000
b11001 "
b101100 )
b100 A
b0 ;
b1100100000011000001000000011000001010000000100000010100101100 *
b1100100000011000001000000011000001010000000100000010100101100 :
b1100100000011000001000000011000001010000000100000010100101100 >
13
#128000
03
#129000
b1 A
b1 @
13
#130000
03
#131000
b10 ;
b10 A
b101 ?
13
#132000
03
#133000
b11 ;
13
#134000
03
#135000
b101 &
b1010 (
b100 ;
b1100100000011000001000000011000000101000000100000101000101100 *
b1100100000011000001000000011000000101000000100000101000101100 :
b1100100000011000001000000011000000101000000100000101000101100 >
13
#136000
03
#137000
b101 ;
13
#138000
03
#139000
b110 ;
13
#140000
03
#141000
b111 ;
13
#142000
03
#143000
b1010 "
b11001 (
b100 A
b0 ;
b101000000011000001000000011000000101000000100001100100101100 *
b101000000011000001000000011000000101000000100001100100101100 :
b101000000011000001000000011000000101000000100001100100101100 >
13
#144000
03
#145000
b1 A
b10 @
13
#146000
03
#147000
b11 ;
b10 A
b10 ?
13
#148000
03
#149000
b10 &
b101 '
b100 ;
b101000000011000001000000011000000010000001010001100100101100 *
b101000000011000001000000011000000010000001010001100100101100 :
b101000000011000001000000011000000010000001010001100100101100 >
13
#150000
03
#151000
b101 %
b110 '
b101 ;
b101000000011000001000000010100000010000001100001100100101100 *
b101000000011000001000000010100000010000001100001100100101100 :
b101000000011000001000000010100000010000001100001100100101100 >
13
#152000
03
#153000
b110 ;
13
#154000
03
#155000
b111 ;
13
#156000
03
#157000
b110 "
b1010 '
b100 A
b0 ;
b11000000011000001000000010100000010000010100001100100101100 *
b11000000011000001000000010100000010000010100001100100101100 :
b11000000011000001000000010100000010000010100001100100101100 >
13
#158000
03
#159000
b1 A
b11 @
13
#160000
03
#161000
b100 ;
b10 A
13
#162000
03
#163000
b10 %
b101 &
b101 ;
b11000000011000001000000001000000101000010100001100100101100 *
b11000000011000001000000001000000101000010100001100100101100 :
b11000000011000001000000001000000101000010100001100100101100 >
13
#164000
03
#165000
b110 ;
13
#166000
03
#167000
b111 ;
13
#168000
03
#169000
b101 "
b110 &
b100 A
b0 ;
b10100000011000001000000001000000110000010100001100100101100 *
b10100000011000001000000001000000110000010100001100100101100 :
b10100000011000001000000001000000110000010100001100100101100 >
13
#170000
03
#171000
b1 A
b100 @
13
#172000
03
#173000
b101 ;
b10 A
13
#174000
03
#175000
b10 $
b100 %
b110 ;
b10100000011000000100000010000000110000010100001100100101100 *
b10100000011000000100000010000000110000010100001100100101100 :
b10100000011000000100000010000000110000010100001100100101100 >
13
#176000
03
#177000
b111 ;
13
#178000
03
#179000
b100 "
b101 %
b100 A
b0 ;
b10000000011000000100000010100000110000010100001100100101100 *
b10000000011000000100000010100000110000010100001100100101100 :
b10000000011000000100000010100000110000010100001100100101100 >
13
#180000
03
#181000
b1 A
b101 @
13
#182000
03
#183000
b110 ;
b10 A
13
#184000
03
#185000
b10 #
b11 $
b111 ;
b10000000010000000110000010100000110000010100001100100101100 *
b10000000010000000110000010100000110000010100001100100101100 :
b10000000010000000110000010100000110000010100001100100101100 >
13
#186000
03
#187000
b11 "
b100 $
b100 A
b0 ;
b1100000010000001000000010100000110000010100001100100101100 *
b1100000010000001000000010100000110000010100001100100101100 :
b1100000010000001000000010100000110000010100001100100101100 >
13
#188000
03
#189000
b1 A
b110 @
13
#190000
03
#191000
b111 ;
b10 A
13
#192000
03
#193000
b10 "
b11 #
b100 A
b0 ;
b1000000011000001000000010100000110000010100001100100101100 *
b1000000011000001000000010100000110000010100001100100101100 :
b1000000011000001000000010100000110000010100001100100101100 >
13
#194000
03
#195000
b1 A
b111 @
13
#196000
03
#197000
b11 A
13
#198000
03
#199000
b0 A
1!
13
#200000
03
#201000
b0 @
13
